rapidllm/__init__.py
rapidllm/agent.py
rapidllm/tools.py
rapidllm/utils.py
rapidllm-0.5.0.dist-info/licenses/LICENSE
rapidllm-0.5.0.dist-info/METADATA
rapidllm-0.5.0.dist-info/WHEEL
rapidllm-0.5.0.dist-info/top_level.txt
rapidllm-0.5.0.dist-info/RECORD
