Metadata-Version: 2.4
Name: rapidllm
Version: 0.5.0
Summary: A small framework for building predictable multi-tool LLM agents.
Author-email: Patrick Tuyizere <you@example.com>
License: MIT
Project-URL: Homepage, https://github.com/Patk-Tuy/rapidllm
Project-URL: Repository, https://github.com/Patk-Tuy/rapidllm
Requires-Python: >=3.8
License-File: LICENSE
Requires-Dist: litellm>=0.1.0
Dynamic: license-file
